XiguanZhifu/README.md
XiguanZhifu/__init__.py
XiguanZhifu/__main__.py
XiguanZhifu/file.epub
XiguanZhifu/index.html
XiguanZhifu/css/__init__.py
XiguanZhifu/css/annotations.css
XiguanZhifu/css/main.css
XiguanZhifu/css/normalize.css
XiguanZhifu/css/popup.css
XiguanZhifu/font/__init__.py
XiguanZhifu/font/fontello.eot
XiguanZhifu/font/fontello.svg
XiguanZhifu/font/fontello.ttf
XiguanZhifu/font/fontello.woff
XiguanZhifu/img/__init__.py
XiguanZhifu/img/annotator-glyph-sprite.png
XiguanZhifu/img/annotator-icon-sprite.png
XiguanZhifu/img/apple-touch-icon.png
XiguanZhifu/img/cancelfullscreen.png
XiguanZhifu/img/close.png
XiguanZhifu/img/fullscreen.png
XiguanZhifu/img/loader.gif
XiguanZhifu/img/menu-icon.png
XiguanZhifu/img/save.png
XiguanZhifu/img/saved.png
XiguanZhifu/img/settings-s.png
XiguanZhifu/img/settings.png
XiguanZhifu/img/star.png
XiguanZhifu/js/__init__.py
XiguanZhifu/js/epub.js
XiguanZhifu/js/epub.min.js
XiguanZhifu/js/epub.min.map
XiguanZhifu/js/hooks.min.js
XiguanZhifu/js/hooks.min.map
XiguanZhifu/js/reader.js
XiguanZhifu/js/reader.js.map
XiguanZhifu/js/reader.min.js
XiguanZhifu/js/reader.min.map
XiguanZhifu/js/hooks/__init__.py
XiguanZhifu/js/hooks/extensions/__init__.py
XiguanZhifu/js/hooks/extensions/highlight.js
XiguanZhifu/js/libs/__init__.py
XiguanZhifu/js/libs/jquery.min.js
XiguanZhifu/js/libs/localforage.min.js
XiguanZhifu/js/libs/screenfull.js
XiguanZhifu/js/libs/screenfull.min.js
XiguanZhifu/js/libs/zip.min.js
XiguanZhifu/js/plugins/__init__.py
XiguanZhifu/js/plugins/hypothesis.js
XiguanZhifu/js/plugins/search.js
xiguan_zhifu-2022.10.15.0.dist-info/METADATA
xiguan_zhifu-2022.10.15.0.dist-info/WHEEL
xiguan_zhifu-2022.10.15.0.dist-info/entry_points.txt
xiguan_zhifu-2022.10.15.0.dist-info/top_level.txt
xiguan_zhifu-2022.10.15.0.dist-info/RECORD
